xgo_spider_log/__init__.py
xgo_spider_log-0.0.11.dist-info/METADATA
xgo_spider_log-0.0.11.dist-info/WHEEL
xgo_spider_log-0.0.11.dist-info/top_level.txt
xgo_spider_log-0.0.11.dist-info/RECORD
