Metadata-Version: 2.1
Name: xgo-spider-log
Version: 0.0.11
Summary: XGo 爬虫日志
Home-page: https://github.com/xgoteam/xgo-spider-log
Author: cielpy
Author-email: beijiu572@gmail.com
License: UNKNOWN
Platform: UNKNOWN
